{
  "id": "piface-adapter",
  "name": "PiFace",
  "description": "Connect your PiFace HAT",
  "author": "Tim Hellhake",
  "homepage_url": "https://github.com/tim-hellhake/piface-adapter#readme",
  "license_url": "https://raw.githubusercontent.com/tim-hellhake/piface-adapter/master/LICENSE",
  "primary_type": "adapter",
  "packages": [
    {
      "architecture": "linux-arm",
      "language": {
        "name": "nodejs",
        "versions": [
          "57"
        ]
      },
      "version": "0.1.1",
      "url": "https://github.com/tim-hellhake/piface-adapter/releases/download/0.1.1/piface-adapter-0.1.1-linux-arm-v8.tgz",
      "checksum": "7c8380b4f94723ab5f19b65ee730e710288511164de0cd86df85bc6c702ef72b",
      "gateway": {
        "min": "0.10.0",
        "max": "*"
      }
    },
    {
      "architecture": "linux-arm",
      "language": {
        "name": "nodejs",
        "versions": [
          "64"
        ]
      },
      "version": "0.1.1",
      "url": "https://github.com/tim-hellhake/piface-adapter/releases/download/0.1.1/piface-adapter-0.1.1-linux-arm-v10.tgz",
      "checksum": "59eb02addc99f1fd32684eda5de0e63926856003ebb85a764e4fbc71c2bfc3dd",
      "gateway": {
        "min": "0.10.0",
        "max": "*"
      }
    },
    {
      "architecture": "linux-arm",
      "language": {
        "name": "nodejs",
        "versions": [
          "72"
        ]
      },
      "version": "0.1.1",
      "url": "https://github.com/tim-hellhake/piface-adapter/releases/download/0.1.1/piface-adapter-0.1.1-linux-arm-v12.tgz",
      "checksum": "4fcb536cd1801c831f32abb773dc73f27aa52ab1be7c594892107440f7e552c3",
      "gateway": {
        "min": "0.10.0",
        "max": "*"
      }
    }
  ]
}
